pyscaffold_interactive/__init__.py
pyscaffold_interactive/cli.py
pyscaffold_interactive-0.3.0.dist-info/entry_points.txt
pyscaffold_interactive-0.3.0.dist-info/LICENSE.txt
pyscaffold_interactive-0.3.0.dist-info/WHEEL
pyscaffold_interactive-0.3.0.dist-info/METADATA
pyscaffold_interactive-0.3.0.dist-info/RECORD
