Metadata-Version: 2.1
Name: pyscaffold-interactive
Version: 0.3.0
Summary: Interactive PyScaffold - An interactive Python project template generator based on PyScaffold
License: MIT
Author: Sarthak Jariwala
Requires-Python: >=3.7,<4.0
Classifier: License :: OSI Approved :: MIT License
Classifier: Programming Language :: Python :: 3
Classifier: Programming Language :: Python :: 3.10
Classifier: Programming Language :: Python :: 3.7
Classifier: Programming Language :: Python :: 3.8
Classifier: Programming Language :: Python :: 3.9
Requires-Dist: PyScaffold[all] (>=4.2.1,<5.0.0)
Requires-Dist: click (>=8.1.2,<9.0.0)
